numdoclint/__init__.py
numdoclint/cli.py
numdoclint/helper.py
numdoclint/jupyter_notebook.py
numdoclint/py_module.py
tests/__init__.py
tests/test_cli.py
tests/test_helper.py
tests/test_jupyter_notebook.py
tests/test_numdoclint.py
tests/test_py_module.py
numdoclint-0.1.9.dist-info/LICENSE
numdoclint-0.1.9.dist-info/METADATA
numdoclint-0.1.9.dist-info/WHEEL
numdoclint-0.1.9.dist-info/entry_points.txt
numdoclint-0.1.9.dist-info/top_level.txt
numdoclint-0.1.9.dist-info/RECORD
