Metadata-Version: 2.1
Name: numdoclint
Version: 0.1.9
Summary: Numdoc Lint provides features such as NumPy style docstring code checking.
Home-page: https://github.com/simon-ritchie/numdoclint
Author: simon-ritchie
Author-email: 
Maintainer: simon-ritchie
Maintainer-email: 
License: MIT
Platform: UNKNOWN
Classifier: Programming Language :: Python :: 3
Classifier: License :: OSI Approved :: MIT License
Requires-Dist: six
